mcp_ngobrol/__init__.py
mcp_ngobrol/__main__.py
mcp_ngobrol/auto_mcp_setup.py
mcp_ngobrol/debug.py
mcp_ngobrol/i18n.py
mcp_ngobrol/mcp_environment.py
mcp_ngobrol/server.py
mcp_ngobrol/test_mcp_enhanced.py
mcp_ngobrol/test_qt_gui.py
mcp_ngobrol/gui/__init__.py
mcp_ngobrol/gui/main.py
mcp_ngobrol/gui/locales/README.md
mcp_ngobrol/gui/locales/en/translations.json
mcp_ngobrol/gui/locales/id/translations.json
mcp_ngobrol/gui/locales/zh-CN/translations.json
mcp_ngobrol/gui/locales/zh-TW/translations.json
mcp_ngobrol/gui/models/__init__.py
mcp_ngobrol/gui/models/feedback.py
mcp_ngobrol/gui/styles/__init__.py
mcp_ngobrol/gui/styles/themes.py
mcp_ngobrol/gui/tabs/__init__.py
mcp_ngobrol/gui/tabs/about_tab.py
mcp_ngobrol/gui/tabs/auto_completion_tab.py
mcp_ngobrol/gui/tabs/command_tab.py
mcp_ngobrol/gui/tabs/feedback_tab.py
mcp_ngobrol/gui/tabs/settings_tab.py
mcp_ngobrol/gui/tabs/summary_tab.py
mcp_ngobrol/gui/utils/__init__.py
mcp_ngobrol/gui/utils/shortcuts.py
mcp_ngobrol/gui/utils/utils.py
mcp_ngobrol/gui/widgets/__init__.py
mcp_ngobrol/gui/widgets/image_preview.py
mcp_ngobrol/gui/widgets/image_upload.py
mcp_ngobrol/gui/widgets/styled_spinbox.py
mcp_ngobrol/gui/widgets/switch.py
mcp_ngobrol/gui/widgets/text_edit.py
mcp_ngobrol/gui/widgets/timeout_widget.py
mcp_ngobrol/gui/window/__init__.py
mcp_ngobrol/gui/window/command_executor.py
mcp_ngobrol/gui/window/config_manager.py
mcp_ngobrol/gui/window/feedback_window.py
mcp_ngobrol/gui/window/tab_manager.py
mcp_ngobrol/memory/__init__.py
mcp_ngobrol/memory/context_processor.py
mcp_ngobrol/memory/preference_manager.py
mcp_ngobrol/memory/response_enhancer.py
mcp_ngobrol/memory/session_memory.py
mcp_ngobrol/models/__init__.py
mcp_ngobrol/models/checkpoint.py
mcp_ngobrol/models/completion_trigger.py
mcp_ngobrol/testing/__init__.py
mcp_ngobrol/testing/config.py
mcp_ngobrol/testing/mcp_client.py
mcp_ngobrol/testing/reporter.py
mcp_ngobrol/testing/scenarios.py
mcp_ngobrol/testing/utils.py
mcp_ngobrol/testing/validators.py
mcp_ngobrol-1.0.6.dist-info/METADATA
mcp_ngobrol-1.0.6.dist-info/WHEEL
mcp_ngobrol-1.0.6.dist-info/entry_points.txt
mcp_ngobrol-1.0.6.dist-info/licenses/LICENSE
mcp_ngobrol-1.0.6.dist-info/RECORD
