Metadata-Version: 2.4
Name: mcp-ngobrol
Version: 1.0.6
Summary: MCP server untuk ngobrol interaktif dengan AI - Enhanced feedback system dengan Qt GUI interface yang powerful dan user-friendly.
Project-URL: Homepage, https://github.com/mbprcc/mcp-ngobrol
Project-URL: Repository, https://github.com/mbprcc/mcp-ngobrol
Project-URL: Issues, https://github.com/mbprcc/mcp-ngobrol/issues
Project-URL: Discord, https://social.mbpr.cc/mbprdiscord
Author-email: MBPR <mbpr.dev@gmail.com>
License-File: LICENSE
Keywords: ai,development,feedback,gui,indonesia,interactive,mcp,ngobrol,qt
Classifier: Development Status :: 4 - Beta
Classifier: Intended Audience :: Developers
Classifier: License :: OSI Approved :: MIT License
Classifier: Programming Language :: Python :: 3
Classifier: Programming Language :: Python :: 3.11
Classifier: Programming Language :: Python :: 3.12
Classifier: Topic :: Software Development :: Libraries :: Python Modules
Classifier: Topic :: Software Development :: User Interfaces
Requires-Python: >=3.11
Requires-Dist: fastmcp>=2.0.0
Requires-Dist: psutil>=7.0.0
Requires-Dist: pyside6>=6.8.2.1
Provides-Extra: dev
Requires-Dist: pytest-asyncio>=0.21.0; extra == 'dev'
Requires-Dist: pytest>=7.0.0; extra == 'dev'
